{
  "leadArticles": [
    {
      "hasVideo": false,
      "contentType": "Interview",
      "label": "Martin Samuel",
      "expirableFlags": [
        {
          "type": "BREAKING",
          "expiryTime": null
        }
      ],
      "id": "1",
      "headline": "1 Sarcacens an inclusive club? They didnt look out for me",
      "shortSummary": "160 C. count, turn down United’s bid for Mason Mount while Brentford have a club-record offer of £30 million for Brennan Johnson rejected turn down United’s bid",
      "images": {
        "alt": "",
        "credits": "Gareth Fuller/Press Association",
        "caption": "Sarcacens an inclusive club? They didnt look",
        "crops": [
          {
            "url": "https://www.thetimes.co.uk/imageserver/image/%2Fmethode%2Ftimes%2Fprod%2Fweb%2Fbin%2Fbde50bea-247f-11ee-8c1b-d5d52b458fbd.jpg?crop=3844%2C2563%2C188%2C173",
            "ratio": "3:2"
          },
          {
            "url": "https://www.thetimes.co.uk/imageserver/image/%2Fmethode%2Ftimes%2Fprod%2Fweb%2Fbin%2Fbde50bea-247f-11ee-8c1b-d5d52b458fbd.jpg?crop=2497%2C1405%2C1041%2C169",
            "ratio": "16:9"
          },
          {
            "url": "https://www.thetimes.co.uk/imageserver/image/%2Fmethode%2Ftimes%2Fprod%2Fweb%2Fbin%2Fbde50bea-247f-11ee-8c1b-d5d52b458fbd.jpg?crop=2563%2C2563%2C828%2C173",
            "ratio": "1:1"
          },
          {
            "url": "https://www.thetimes.co.uk/imageserver/image/%2Fmethode%2Ftimes%2Fprod%2Fweb%2Fbin%2Fbde50bea-247f-11ee-8c1b-d5d52b458fbd.jpg?crop=1708%2C2563%2C1256%2C173",
            "ratio": "2:3"
          },
          {
            "url": "https://www.thetimes.co.uk/imageserver/image/%2Fmethode%2Ftimes%2Fprod%2Fweb%2Fbin%2F82edcbd6-778a-11ee-9496-ba645d21d0d9.jpg?crop=6117%2C3441%2C49%2C551",
            "ratio": "4:5"
          },
          {
            "url": "https://www.thetimes.co.uk/imageserver/image/%2Fmethode%2Ftimes%2Fprod%2Fweb%2Fbin%2F6d78b116-7759-11ee-b999-2580d8ced837.jpg?crop=3868%2C2176%2C961%2C98",
            "ratio": "5:4"
          }
        ]
      },

      "url": "https://www.thetimes.co.uk",
      "tag": {
        "label": "Review",
        "href": "/"
      },
      "flag": "The Times",
      "datePublished": "2023-12-11T16:00:00.000Z",
      "byline": "ibrahim"
    },

    {
      "hasVideo": false,
      "contentType": "Interview",
      "label": "Martin Samuel",
      "expirableFlags": [
        {
          "type": "BREAKING",
          "expiryTime": null
        }
      ],
      "id": "2",
      "headline": "2 Sarcacens an inclusive club? They didnt look out for me",
      "shortSummary": "160 C. count, turn down United’s bid for Mason Mount while Brentford have a club-record offer of £30 million for Brennan Johnson rejected turn down United’s bid",
      "images": {
        "alt": "",
        "credits": "Gareth Fuller/Press Association",
        "caption": "Sarcacens an inclusive club? They didnt look",
        "crops": [
          {
            "url": "https://www.thetimes.co.uk/imageserver/image/%2Fmethode%2Ftimes%2Fprod%2Fweb%2Fbin%2Fbde50bea-247f-11ee-8c1b-d5d52b458fbd.jpg?crop=3844%2C2563%2C188%2C173",
            "ratio": "3:2"
          },
          {
            "url": "https://www.thetimes.co.uk/imageserver/image/%2Fmethode%2Ftimes%2Fprod%2Fweb%2Fbin%2Fbde50bea-247f-11ee-8c1b-d5d52b458fbd.jpg?crop=2497%2C1405%2C1041%2C169",
            "ratio": "16:9"
          },
          {
            "url": "https://www.thetimes.co.uk/imageserver/image/%2Fmethode%2Ftimes%2Fprod%2Fweb%2Fbin%2Fbde50bea-247f-11ee-8c1b-d5d52b458fbd.jpg?crop=2563%2C2563%2C828%2C173",
            "ratio": "1:1"
          },
          {
            "url": "https://www.thetimes.co.uk/imageserver/image/%2Fmethode%2Ftimes%2Fprod%2Fweb%2Fbin%2Fbde50bea-247f-11ee-8c1b-d5d52b458fbd.jpg?crop=1708%2C2563%2C1256%2C173",
            "ratio": "2:3"
          },
          {
            "url": "https://www.thetimes.co.uk/imageserver/image/%2Fmethode%2Ftimes%2Fprod%2Fweb%2Fbin%2F82edcbd6-778a-11ee-9496-ba645d21d0d9.jpg?crop=6117%2C3441%2C49%2C551",
            "ratio": "4:5"
          },
          {
            "url": "https://www.thetimes.co.uk/imageserver/image/%2Fmethode%2Ftimes%2Fprod%2Fweb%2Fbin%2F6d78b116-7759-11ee-b999-2580d8ced837.jpg?crop=3868%2C2176%2C961%2C98",
            "ratio": "5:4"
          }
        ]
      },

      "url": "https://www.thetimes.co.uk",
      "tag": {
        "label": "Review",
        "href": "/"
      },
      "flag": "The Times",
      "datePublished": "2023-04-11T16:00:00.000Z",
      "byline": "ibrahim"
    },
    {
      "hasVideo": false,
      "contentType": "Interview",
      "label": "Martin Samuel",
      "expirableFlags": [
        {
          "type": "BREAKING",
          "expiryTime": null
        }
      ],
      "id": "3",
      "headline": "3 Sarcacens an inclusive club? They didnt look out for me",
      "shortSummary": "160 C. count, turn down United’s bid for Mason Mount while Brentford have a club-record offer of £30 million for Brennan Johnson rejected turn down United’s bid",
      "images": {
        "alt": "",
        "credits": "Gareth Fuller/Press Association",
        "caption": "Sarcacens an inclusive club? They didnt look",
        "crops": [
          {
            "url": "https://www.thetimes.co.uk/imageserver/image/%2Fmethode%2Ftimes%2Fprod%2Fweb%2Fbin%2Fbde50bea-247f-11ee-8c1b-d5d52b458fbd.jpg?crop=3844%2C2563%2C188%2C173",
            "ratio": "3:2"
          },
          {
            "url": "https://www.thetimes.co.uk/imageserver/image/%2Fmethode%2Ftimes%2Fprod%2Fweb%2Fbin%2Fbde50bea-247f-11ee-8c1b-d5d52b458fbd.jpg?crop=2497%2C1405%2C1041%2C169",
            "ratio": "16:9"
          },
          {
            "url": "https://www.thetimes.co.uk/imageserver/image/%2Fmethode%2Ftimes%2Fprod%2Fweb%2Fbin%2Fbde50bea-247f-11ee-8c1b-d5d52b458fbd.jpg?crop=2563%2C2563%2C828%2C173",
            "ratio": "1:1"
          },
          {
            "url": "https://www.thetimes.co.uk/imageserver/image/%2Fmethode%2Ftimes%2Fprod%2Fweb%2Fbin%2Fbde50bea-247f-11ee-8c1b-d5d52b458fbd.jpg?crop=1708%2C2563%2C1256%2C173",
            "ratio": "2:3"
          },
          {
            "url": "https://www.thetimes.co.uk/imageserver/image/%2Fmethode%2Ftimes%2Fprod%2Fweb%2Fbin%2F82edcbd6-778a-11ee-9496-ba645d21d0d9.jpg?crop=6117%2C3441%2C49%2C551",
            "ratio": "4:5"
          },
          {
            "url": "https://www.thetimes.co.uk/imageserver/image/%2Fmethode%2Ftimes%2Fprod%2Fweb%2Fbin%2F6d78b116-7759-11ee-b999-2580d8ced837.jpg?crop=3868%2C2176%2C961%2C98",
            "ratio": "5:4"
          }
        ]
      },

      "url": "https://www.thetimes.co.uk",
      "tag": {
        "label": "Review",
        "href": "/"
      },
      "flag": "The Sunday Times",
      "datePublished": "2023-02-11T16:00:00.000Z",
      "byline": "ibrahim"
    },
    {
      "hasVideo": false,
      "contentType": "Interview",
      "label": "Martin Samuel",
      "expirableFlags": [
        {
          "type": "BREAKING",
          "expiryTime": null
        }
      ],
      "id": "4",
      "headline": "4 Sarcacens an inclusive club? They didnt look out for me",
      "shortSummary": "160 C. count, turn down United’s bid for Mason Mount while Brentford have a club-record offer of £30 million for Brennan Johnson rejected turn down United’s bid",
      "images": {
        "alt": "",
        "credits": "Gareth Fuller/Press Association",
        "caption": "Sarcacens an inclusive club? They didnt look",
        "crops": [
          {
            "url": "https://www.thetimes.co.uk/imageserver/image/%2Fmethode%2Ftimes%2Fprod%2Fweb%2Fbin%2Fbde50bea-247f-11ee-8c1b-d5d52b458fbd.jpg?crop=3844%2C2563%2C188%2C173",
            "ratio": "3:2"
          },
          {
            "url": "https://www.thetimes.co.uk/imageserver/image/%2Fmethode%2Ftimes%2Fprod%2Fweb%2Fbin%2Fbde50bea-247f-11ee-8c1b-d5d52b458fbd.jpg?crop=2497%2C1405%2C1041%2C169",
            "ratio": "16:9"
          },
          {
            "url": "https://www.thetimes.co.uk/imageserver/image/%2Fmethode%2Ftimes%2Fprod%2Fweb%2Fbin%2Fbde50bea-247f-11ee-8c1b-d5d52b458fbd.jpg?crop=2563%2C2563%2C828%2C173",
            "ratio": "1:1"
          },
          {
            "url": "https://www.thetimes.co.uk/imageserver/image/%2Fmethode%2Ftimes%2Fprod%2Fweb%2Fbin%2Fbde50bea-247f-11ee-8c1b-d5d52b458fbd.jpg?crop=1708%2C2563%2C1256%2C173",
            "ratio": "2:3"
          },
          {
            "url": "https://www.thetimes.co.uk/imageserver/image/%2Fmethode%2Ftimes%2Fprod%2Fweb%2Fbin%2F82edcbd6-778a-11ee-9496-ba645d21d0d9.jpg?crop=6117%2C3441%2C49%2C551",
            "ratio": "4:5"
          },
          {
            "url": "https://www.thetimes.co.uk/imageserver/image/%2Fmethode%2Ftimes%2Fprod%2Fweb%2Fbin%2F6d78b116-7759-11ee-b999-2580d8ced837.jpg?crop=3868%2C2176%2C961%2C98",
            "ratio": "5:4"
          }
        ]
      },

      "url": "https://www.thetimes.co.uk",
      "tag": {
        "label": "Review",
        "href": "/"
      },
      "flag": "The Times",
      "datePublished": "2023-11-11T16:00:00.000Z",
      "byline": "ibrahim"
    },
    {
      "hasVideo": false,
      "contentType": "Interview",
      "label": "Martin Samuel",
      "expirableFlags": [
        {
          "type": "BREAKING",
          "expiryTime": null
        }
      ],
      "id": "5",
      "headline": "5 Sarcacens an inclusive club? They didnt look out for me",
      "shortSummary": "160 C. count, turn down United’s bid for Mason Mount while Brentford have a club-record offer of £30 million for Brennan Johnson rejected turn down United’s bid",
      "images": {
        "alt": "",
        "credits": "Gareth Fuller/Press Association",
        "caption": "Sarcacens an inclusive club? They didnt look",
        "crops": [
          {
            "url": "https://www.thetimes.co.uk/imageserver/image/%2Fmethode%2Ftimes%2Fprod%2Fweb%2Fbin%2Fbde50bea-247f-11ee-8c1b-d5d52b458fbd.jpg?crop=3844%2C2563%2C188%2C173",
            "ratio": "3:2"
          },
          {
            "url": "https://www.thetimes.co.uk/imageserver/image/%2Fmethode%2Ftimes%2Fprod%2Fweb%2Fbin%2Fbde50bea-247f-11ee-8c1b-d5d52b458fbd.jpg?crop=2497%2C1405%2C1041%2C169",
            "ratio": "16:9"
          },
          {
            "url": "https://www.thetimes.co.uk/imageserver/image/%2Fmethode%2Ftimes%2Fprod%2Fweb%2Fbin%2Fbde50bea-247f-11ee-8c1b-d5d52b458fbd.jpg?crop=2563%2C2563%2C828%2C173",
            "ratio": "1:1"
          },
          {
            "url": "https://www.thetimes.co.uk/imageserver/image/%2Fmethode%2Ftimes%2Fprod%2Fweb%2Fbin%2Fbde50bea-247f-11ee-8c1b-d5d52b458fbd.jpg?crop=1708%2C2563%2C1256%2C173",
            "ratio": "2:3"
          },
          {
            "url": "https://www.thetimes.co.uk/imageserver/image/%2Fmethode%2Ftimes%2Fprod%2Fweb%2Fbin%2F82edcbd6-778a-11ee-9496-ba645d21d0d9.jpg?crop=6117%2C3441%2C49%2C551",
            "ratio": "4:5"
          },
          {
            "url": "https://www.thetimes.co.uk/imageserver/image/%2Fmethode%2Ftimes%2Fprod%2Fweb%2Fbin%2F6d78b116-7759-11ee-b999-2580d8ced837.jpg?crop=3868%2C2176%2C961%2C98",
            "ratio": "5:4"
          }
        ]
      },

      "url": "https://www.thetimes.co.uk",
      "tag": {
        "label": "Review",
        "href": "/"
      },
      "flag": "The Sunday Times",
      "datePublished": "2023-11-11T16:00:00.000Z",
      "byline": "ibrahim"
    },
    {
      "hasVideo": false,
      "contentType": "Interview",
      "label": "Martin Samuel",
      "expirableFlags": [
        {
          "type": "BREAKING",
          "expiryTime": null
        }
      ],
      "id": "6",
      "headline": "6 Sarcacens an inclusive club? They didnt look out for me",
      "shortSummary": "160 C. count, turn down United’s bid for Mason Mount while Brentford have a club-record offer of £30 million for Brennan Johnson rejected turn down United’s bid",
      "images": {
        "alt": "",
        "credits": "Gareth Fuller/Press Association",
        "caption": "Sarcacens an inclusive club? They didnt look",
        "crops": [
          {
            "url": "https://www.thetimes.co.uk/imageserver/image/%2Fmethode%2Ftimes%2Fprod%2Fweb%2Fbin%2Fbde50bea-247f-11ee-8c1b-d5d52b458fbd.jpg?crop=3844%2C2563%2C188%2C173",
            "ratio": "3:2"
          },
          {
            "url": "https://www.thetimes.co.uk/imageserver/image/%2Fmethode%2Ftimes%2Fprod%2Fweb%2Fbin%2Fbde50bea-247f-11ee-8c1b-d5d52b458fbd.jpg?crop=2497%2C1405%2C1041%2C169",
            "ratio": "16:9"
          },
          {
            "url": "https://www.thetimes.co.uk/imageserver/image/%2Fmethode%2Ftimes%2Fprod%2Fweb%2Fbin%2Fbde50bea-247f-11ee-8c1b-d5d52b458fbd.jpg?crop=2563%2C2563%2C828%2C173",
            "ratio": "1:1"
          },
          {
            "url": "https://www.thetimes.co.uk/imageserver/image/%2Fmethode%2Ftimes%2Fprod%2Fweb%2Fbin%2Fbde50bea-247f-11ee-8c1b-d5d52b458fbd.jpg?crop=1708%2C2563%2C1256%2C173",
            "ratio": "2:3"
          },
          {
            "url": "https://www.thetimes.co.uk/imageserver/image/%2Fmethode%2Ftimes%2Fprod%2Fweb%2Fbin%2F82edcbd6-778a-11ee-9496-ba645d21d0d9.jpg?crop=6117%2C3441%2C49%2C551",
            "ratio": "4:5"
          },
          {
            "url": "https://www.thetimes.co.uk/imageserver/image/%2Fmethode%2Ftimes%2Fprod%2Fweb%2Fbin%2F6d78b116-7759-11ee-b999-2580d8ced837.jpg?crop=3868%2C2176%2C961%2C98",
            "ratio": "5:4"
          }
        ]
      },

      "url": "https://www.thetimes.co.uk",
      "tag": {
        "label": "Review",
        "href": "/"
      },
      "flag": "The Times",
      "datePublished": "2023-10-11T16:00:00.000Z",
      "byline": "ibrahim"
    },
    {
      "hasVideo": false,
      "contentType": "Interview",
      "label": "Martin Samuel",
      "expirableFlags": [
        {
          "type": "BREAKING",
          "expiryTime": null
        }
      ],
      "id": "7",
      "headline": "7 Sarcacens an inclusive club? They didnt look out for me",
      "shortSummary": "160 C. count, turn down United’s bid for Mason Mount while Brentford have a club-record offer of £30 million for Brennan Johnson rejected turn down United’s bid",
      "images": {
        "alt": "",
        "credits": "Gareth Fuller/Press Association",
        "caption": "Sarcacens an inclusive club? They didnt look",
        "crops": [
          {
            "url": "https://www.thetimes.co.uk/imageserver/image/%2Fmethode%2Ftimes%2Fprod%2Fweb%2Fbin%2Fbde50bea-247f-11ee-8c1b-d5d52b458fbd.jpg?crop=3844%2C2563%2C188%2C173",
            "ratio": "3:2"
          },
          {
            "url": "https://www.thetimes.co.uk/imageserver/image/%2Fmethode%2Ftimes%2Fprod%2Fweb%2Fbin%2Fbde50bea-247f-11ee-8c1b-d5d52b458fbd.jpg?crop=2497%2C1405%2C1041%2C169",
            "ratio": "16:9"
          },
          {
            "url": "https://www.thetimes.co.uk/imageserver/image/%2Fmethode%2Ftimes%2Fprod%2Fweb%2Fbin%2Fbde50bea-247f-11ee-8c1b-d5d52b458fbd.jpg?crop=2563%2C2563%2C828%2C173",
            "ratio": "1:1"
          },
          {
            "url": "https://www.thetimes.co.uk/imageserver/image/%2Fmethode%2Ftimes%2Fprod%2Fweb%2Fbin%2Fbde50bea-247f-11ee-8c1b-d5d52b458fbd.jpg?crop=1708%2C2563%2C1256%2C173",
            "ratio": "2:3"
          },
          {
            "url": "https://www.thetimes.co.uk/imageserver/image/%2Fmethode%2Ftimes%2Fprod%2Fweb%2Fbin%2F82edcbd6-778a-11ee-9496-ba645d21d0d9.jpg?crop=6117%2C3441%2C49%2C551",
            "ratio": "4:5"
          },
          {
            "url": "https://www.thetimes.co.uk/imageserver/image/%2Fmethode%2Ftimes%2Fprod%2Fweb%2Fbin%2F6d78b116-7759-11ee-b999-2580d8ced837.jpg?crop=3868%2C2176%2C961%2C98",
            "ratio": "5:4"
          }
        ]
      },

      "url": "https://www.thetimes.co.uk",
      "tag": {
        "label": "Review",
        "href": "/"
      },
      "flag": "The Sunday Times",
      "datePublished": "2023-09-11T16:00:00.000Z",
      "byline": "ibrahim kurhan"
    },
    {
      "hasVideo": false,
      "contentType": "Interview",
      "label": "Martin Samuel",
      "expirableFlags": [
        {
          "type": "BREAKING",
          "expiryTime": null
        }
      ],
      "id": "8",
      "headline": "8 Sarcacens an inclusive club? They didnt look out for me",
      "shortSummary": "160 C. count, turn down United’s bid for Mason Mount while Brentford have a club-record offer of £30 million for Brennan Johnson rejected turn down United’s bid",
      "images": {
        "alt": "",
        "credits": "Gareth Fuller/Press Association",
        "caption": "Sarcacens an inclusive club? They didnt look",
        "crops": [
          {
            "url": "https://www.thetimes.co.uk/imageserver/image/%2Fmethode%2Ftimes%2Fprod%2Fweb%2Fbin%2Fbde50bea-247f-11ee-8c1b-d5d52b458fbd.jpg?crop=3844%2C2563%2C188%2C173",
            "ratio": "3:2"
          },
          {
            "url": "https://www.thetimes.co.uk/imageserver/image/%2Fmethode%2Ftimes%2Fprod%2Fweb%2Fbin%2Fbde50bea-247f-11ee-8c1b-d5d52b458fbd.jpg?crop=2497%2C1405%2C1041%2C169",
            "ratio": "16:9"
          },
          {
            "url": "https://www.thetimes.co.uk/imageserver/image/%2Fmethode%2Ftimes%2Fprod%2Fweb%2Fbin%2Fbde50bea-247f-11ee-8c1b-d5d52b458fbd.jpg?crop=2563%2C2563%2C828%2C173",
            "ratio": "1:1"
          },
          {
            "url": "https://www.thetimes.co.uk/imageserver/image/%2Fmethode%2Ftimes%2Fprod%2Fweb%2Fbin%2Fbde50bea-247f-11ee-8c1b-d5d52b458fbd.jpg?crop=1708%2C2563%2C1256%2C173",
            "ratio": "2:3"
          },
          {
            "url": "https://www.thetimes.co.uk/imageserver/image/%2Fmethode%2Ftimes%2Fprod%2Fweb%2Fbin%2F82edcbd6-778a-11ee-9496-ba645d21d0d9.jpg?crop=6117%2C3441%2C49%2C551",
            "ratio": "4:5"
          },
          {
            "url": "https://www.thetimes.co.uk/imageserver/image/%2Fmethode%2Ftimes%2Fprod%2Fweb%2Fbin%2F6d78b116-7759-11ee-b999-2580d8ced837.jpg?crop=3868%2C2176%2C961%2C98",
            "ratio": "5:4"
          }
        ]
      },

      "url": "https://www.thetimes.co.uk",
      "tag": {
        "label": "Review",
        "href": "/"
      },
      "flag": "The Times",

      "datePublished": "2023-09-11T16:00:00.000Z",
      "byline": "ibrahim"
    },
    {
      "hasVideo": false,
      "contentType": "Interview",
      "label": "Martin Samuel",
      "expirableFlags": [
        {
          "type": "BREAKING",
          "expiryTime": null
        }
      ],
      "id": "9",
      "headline": "9 Sarcacens an inclusive club? They didnt look out for me",
      "shortSummary": "160 C. count, turn down United’s bid for Mason Mount while Brentford have a club-record offer of £30 million for Brennan Johnson rejected turn down United’s bid",
      "images": {
        "alt": "",
        "credits": "Gareth Fuller/Press Association",
        "caption": "Sarcacens an inclusive club? They didnt look",
        "crops": [
          {
            "url": "https://www.thetimes.co.uk/imageserver/image/%2Fmethode%2Ftimes%2Fprod%2Fweb%2Fbin%2Fbde50bea-247f-11ee-8c1b-d5d52b458fbd.jpg?crop=3844%2C2563%2C188%2C173",
            "ratio": "3:2"
          },
          {
            "url": "https://www.thetimes.co.uk/imageserver/image/%2Fmethode%2Ftimes%2Fprod%2Fweb%2Fbin%2Fbde50bea-247f-11ee-8c1b-d5d52b458fbd.jpg?crop=2497%2C1405%2C1041%2C169",
            "ratio": "16:9"
          },
          {
            "url": "https://www.thetimes.co.uk/imageserver/image/%2Fmethode%2Ftimes%2Fprod%2Fweb%2Fbin%2Fbde50bea-247f-11ee-8c1b-d5d52b458fbd.jpg?crop=2563%2C2563%2C828%2C173",
            "ratio": "1:1"
          },
          {
            "url": "https://www.thetimes.co.uk/imageserver/image/%2Fmethode%2Ftimes%2Fprod%2Fweb%2Fbin%2Fbde50bea-247f-11ee-8c1b-d5d52b458fbd.jpg?crop=1708%2C2563%2C1256%2C173",
            "ratio": "2:3"
          },
          {
            "url": "https://www.thetimes.co.uk/imageserver/image/%2Fmethode%2Ftimes%2Fprod%2Fweb%2Fbin%2F82edcbd6-778a-11ee-9496-ba645d21d0d9.jpg?crop=6117%2C3441%2C49%2C551",
            "ratio": "4:5"
          },
          {
            "url": "https://www.thetimes.co.uk/imageserver/image/%2Fmethode%2Ftimes%2Fprod%2Fweb%2Fbin%2F6d78b116-7759-11ee-b999-2580d8ced837.jpg?crop=3868%2C2176%2C961%2C98",
            "ratio": "5:4"
          }
        ]
      },

      "url": "https://www.thetimes.co.uk",
      "tag": {
        "label": "Review",
        "href": "/"
      },
      "flag": "The Times",
      "datePublished": "2023-06-11T16:00:00.000Z",
      "byline": "ibrahim"
    },
    {
      "hasVideo": false,
      "contentType": "Interview",
      "label": "Martin Samuel",
      "expirableFlags": [
        {
          "type": "BREAKING",
          "expiryTime": null
        }
      ],
      "id": "10",
      "headline": "10 Sarcacens an inclusive club? They didnt look out for me",
      "shortSummary": "160 C. count, turn down United’s bid for Mason Mount while Brentford have a club-record offer of £30 million for Brennan Johnson rejected turn down United’s bid",
      "images": {
        "alt": "",
        "credits": "Gareth Fuller/Press Association",
        "caption": "Sarcacens an inclusive club? They didnt look",
        "crops": [
          {
            "url": "https://www.thetimes.co.uk/imageserver/image/%2Fmethode%2Ftimes%2Fprod%2Fweb%2Fbin%2Fbde50bea-247f-11ee-8c1b-d5d52b458fbd.jpg?crop=3844%2C2563%2C188%2C173",
            "ratio": "3:2"
          },
          {
            "url": "https://www.thetimes.co.uk/imageserver/image/%2Fmethode%2Ftimes%2Fprod%2Fweb%2Fbin%2Fbde50bea-247f-11ee-8c1b-d5d52b458fbd.jpg?crop=2497%2C1405%2C1041%2C169",
            "ratio": "16:9"
          },
          {
            "url": "https://www.thetimes.co.uk/imageserver/image/%2Fmethode%2Ftimes%2Fprod%2Fweb%2Fbin%2Fbde50bea-247f-11ee-8c1b-d5d52b458fbd.jpg?crop=2563%2C2563%2C828%2C173",
            "ratio": "1:1"
          },
          {
            "url": "https://www.thetimes.co.uk/imageserver/image/%2Fmethode%2Ftimes%2Fprod%2Fweb%2Fbin%2Fbde50bea-247f-11ee-8c1b-d5d52b458fbd.jpg?crop=1708%2C2563%2C1256%2C173",
            "ratio": "2:3"
          },
          {
            "url": "https://www.thetimes.co.uk/imageserver/image/%2Fmethode%2Ftimes%2Fprod%2Fweb%2Fbin%2F82edcbd6-778a-11ee-9496-ba645d21d0d9.jpg?crop=6117%2C3441%2C49%2C551",
            "ratio": "4:5"
          },
          {
            "url": "https://www.thetimes.co.uk/imageserver/image/%2Fmethode%2Ftimes%2Fprod%2Fweb%2Fbin%2F6d78b116-7759-11ee-b999-2580d8ced837.jpg?crop=3868%2C2176%2C961%2C98",
            "ratio": "5:4"
          }
        ]
      },

      "url": "https://www.thetimes.co.uk",
      "tag": {
        "label": "Review",
        "href": "/"
      },
      "flag": "The Times",
      "datePublished": "2023-06-11T16:00:00.000Z",
      "byline": "ibrahim"
    }
  ]
}
