{
  "leadArticle": {
    "contentType": "Interview",
    "articleLabel": "Martin Samuel",
    "expirableFlag": "live",
    "id": "1",
    "headline": "Sarcacens an inclusive club? They didnt look out for me",
    "shortSummary": "Lyon lock Joel Kpoku tells Will Kelleher that he’s fired up to face old team — and urges more English stars to move to France",
    "images": {
      "alt": "",
      "credits": "Gareth Fuller/Press Association",
      "caption": "Sarcacens an inclusive club? They didnt look",
      "crops": [
        {
          "url": "https://www.thetimes.co.uk/imageserver/image/%2Fmethode%2Ftimes%2Fprod%2Fweb%2Fbin%2Fbde50bea-247f-11ee-8c1b-d5d52b458fbd.jpg?crop=3844%2C2563%2C188%2C173",
          "ratio": "3:2"
        },
        {
          "url": "https://www.thetimes.co.uk/imageserver/image/%2Fmethode%2Ftimes%2Fprod%2Fweb%2Fbin%2Fbde50bea-247f-11ee-8c1b-d5d52b458fbd.jpg?crop=2497%2C1405%2C1041%2C169",
          "ratio": "16:9"
        },
        {
          "url": "https://www.thetimes.co.uk/imageserver/image/%2Fmethode%2Ftimes%2Fprod%2Fweb%2Fbin%2Fbde50bea-247f-11ee-8c1b-d5d52b458fbd.jpg?crop=2563%2C2563%2C828%2C173",
          "ratio": "1:1"
        },
        {
          "url": "https://www.thetimes.co.uk/imageserver/image/%2Fmethode%2Ftimes%2Fprod%2Fweb%2Fbin%2Fbde50bea-247f-11ee-8c1b-d5d52b458fbd.jpg?crop=1708%2C2563%2C1256%2C173",
          "ratio": "2:3"
        },
        {
          "url": "https://www.thetimes.co.uk/imageserver/image/%2Fmethode%2Ftimes%2Fprod%2Fweb%2Fbin%2Fbde50bea-247f-11ee-8c1b-d5d52b458fbd.jpg?crop=2050%2C2563%2C1085%2C173",
          "ratio": "4:5"
        },
        {
          "url": "https://www.thetimes.co.uk/imageserver/image/%2Fmethode%2Ftimes%2Fprod%2Fweb%2Fbin%2Fbde50bea-247f-11ee-8c1b-d5d52b458fbd.jpg?crop=3203%2C2563%2C508%2C173",
          "ratio": "5:4"
        }
      ]
    },
    "url": "https://www.thetimes.co.uk",
    "tag": {
      "label": "Review",
      "href": "/"
    },
    "flag": "4 min read",
    "listData": []
  },
  "articles": [
    {
      "contentType": "Profile",
      "articleLabel": "",
      "expirableFlag": "Updated",
      "images": {
        "alt": "",
        "credits": "Gareth Fuller/Press Association",
        "caption": "Sarcacens an inclusive club? They didnt look out for me",
        "crops": [
          {
            "url": "https://www.thetimes.co.uk/imageserver/image/%2Fmethode%2Ftimes%2Fprod%2Fweb%2Fbin%2Fbde50bea-247f-11ee-8c1b-d5d52b458fbd.jpg?crop=3844%2C2563%2C188%2C173",
            "ratio": "3:2"
          },
          {
            "url": "https://www.thetimes.co.uk/imageserver/image/%2Fmethode%2Ftimes%2Fprod%2Fweb%2Fbin%2Fbde50bea-247f-11ee-8c1b-d5d52b458fbd.jpg?crop=2497%2C1405%2C1041%2C169",
            "ratio": "16:9"
          },
          {
            "url": "https://www.thetimes.co.uk/imageserver/image/%2Fmethode%2Ftimes%2Fprod%2Fweb%2Fbin%2Fbde50bea-247f-11ee-8c1b-d5d52b458fbd.jpg?crop=2563%2C2563%2C828%2C173",
            "ratio": "1:1"
          },
          {
            "url": "https://www.thetimes.co.uk/imageserver/image/%2Fmethode%2Ftimes%2Fprod%2Fweb%2Fbin%2Fbde50bea-247f-11ee-8c1b-d5d52b458fbd.jpg?crop=1708%2C2563%2C1256%2C173",
            "ratio": "2:3"
          },
          {
            "url": "https://www.thetimes.co.uk/imageserver/image/%2Fmethode%2Ftimes%2Fprod%2Fweb%2Fbin%2Fbde50bea-247f-11ee-8c1b-d5d52b458fbd.jpg?crop=2050%2C2563%2C1085%2C173",
            "ratio": "4:5"
          },
          {
            "url": "https://www.thetimes.co.uk/imageserver/image/%2Fmethode%2Ftimes%2Fprod%2Fweb%2Fbin%2Fbde50bea-247f-11ee-8c1b-d5d52b458fbd.jpg?crop=3203%2C2563%2C508%2C173",
            "ratio": "5:4"
          }
        ]
      },
      "headline": "European cup winner Mihajlovic dies aged 53 after battle with leukaemia",
      "id": "12",
      "url": "/article/harry-and-meghan-s-new-project-to-make-boys-less-toxic-nk5n3h70m",
      "tag": {
        "label": "",
        "href": ""
      },
      "flag": ""
    },
    {
      "contentType": "Review",
      "articleLabel": "",
      "expirableFlag": "exclusive",
      "images": {
        "alt": "",
        "credits": "Gareth Fuller/Press Association",
        "caption": "Sarcacens an inclusive club? They didnt look out for me",
        "crops": [
          {
            "url": "https://www.thetimes.co.uk/imageserver/image/%2Fmethode%2Ftimes%2Fprod%2Fweb%2Fbin%2Fbde50bea-247f-11ee-8c1b-d5d52b458fbd.jpg?crop=3844%2C2563%2C188%2C173",
            "ratio": "3:2"
          },
          {
            "url": "https://www.thetimes.co.uk/imageserver/image/%2Fmethode%2Ftimes%2Fprod%2Fweb%2Fbin%2Fbde50bea-247f-11ee-8c1b-d5d52b458fbd.jpg?crop=2497%2C1405%2C1041%2C169",
            "ratio": "16:9"
          },
          {
            "url": "https://www.thetimes.co.uk/imageserver/image/%2Fmethode%2Ftimes%2Fprod%2Fweb%2Fbin%2Fbde50bea-247f-11ee-8c1b-d5d52b458fbd.jpg?crop=2563%2C2563%2C828%2C173",
            "ratio": "1:1"
          },
          {
            "url": "https://www.thetimes.co.uk/imageserver/image/%2Fmethode%2Ftimes%2Fprod%2Fweb%2Fbin%2Fbde50bea-247f-11ee-8c1b-d5d52b458fbd.jpg?crop=1708%2C2563%2C1256%2C173",
            "ratio": "2:3"
          },
          {
            "url": "https://www.thetimes.co.uk/imageserver/image/%2Fmethode%2Ftimes%2Fprod%2Fweb%2Fbin%2Fbde50bea-247f-11ee-8c1b-d5d52b458fbd.jpg?crop=2050%2C2563%2C1085%2C173",
            "ratio": "4:5"
          },
          {
            "url": "https://www.thetimes.co.uk/imageserver/image/%2Fmethode%2Ftimes%2Fprod%2Fweb%2Fbin%2Fbde50bea-247f-11ee-8c1b-d5d52b458fbd.jpg?crop=3203%2C2563%2C508%2C173",
            "ratio": "5:4"
          }
        ]
      },
      "headline": "‘American owners pose threat to English pyramid’",
      "id": "123",
      "url": "/article/harry-and-meghan-s-new-project-to-make-boys-less-toxic-nk5n3h70m",
      "tag": {
        "label": "",
        "href": ""
      },
      "flag": ""
    },
    {
      "contentType": "Q&A",
      "articleLabel": "",
      "expirableFlag": "Updated",
      "images": {
        "alt": "",
        "credits": "Gareth Fuller/Press Association",
        "caption": "Sarcacens an inclusive club? They didnt look out for me",
        "crops": [
          {
            "url": "https://www.thetimes.co.uk/imageserver/image/%2Fmethode%2Ftimes%2Fprod%2Fweb%2Fbin%2Fbde50bea-247f-11ee-8c1b-d5d52b458fbd.jpg?crop=3844%2C2563%2C188%2C173",
            "ratio": "3:2"
          },
          {
            "url": "https://www.thetimes.co.uk/imageserver/image/%2Fmethode%2Ftimes%2Fprod%2Fweb%2Fbin%2Fbde50bea-247f-11ee-8c1b-d5d52b458fbd.jpg?crop=2497%2C1405%2C1041%2C169",
            "ratio": "16:9"
          },
          {
            "url": "https://www.thetimes.co.uk/imageserver/image/%2Fmethode%2Ftimes%2Fprod%2Fweb%2Fbin%2Fbde50bea-247f-11ee-8c1b-d5d52b458fbd.jpg?crop=2563%2C2563%2C828%2C173",
            "ratio": "1:1"
          },
          {
            "url": "https://www.thetimes.co.uk/imageserver/image/%2Fmethode%2Ftimes%2Fprod%2Fweb%2Fbin%2Fbde50bea-247f-11ee-8c1b-d5d52b458fbd.jpg?crop=1708%2C2563%2C1256%2C173",
            "ratio": "2:3"
          },
          {
            "url": "https://www.thetimes.co.uk/imageserver/image/%2Fmethode%2Ftimes%2Fprod%2Fweb%2Fbin%2Fbde50bea-247f-11ee-8c1b-d5d52b458fbd.jpg?crop=2050%2C2563%2C1085%2C173",
            "ratio": "4:5"
          },
          {
            "url": "https://www.thetimes.co.uk/imageserver/image/%2Fmethode%2Ftimes%2Fprod%2Fweb%2Fbin%2Fbde50bea-247f-11ee-8c1b-d5d52b458fbd.jpg?crop=3203%2C2563%2C508%2C173",
            "ratio": "5:4"
          }
        ]
      },
      "headline": "£60m Brazilian prodigy Endrick snubs Chelsea to join Real Madrid",
      "id": "1234",
      "url": "/article/harry-and-meghan-s-new-project-to-make-boys-less-toxic-nk5n3h70m",
      "tag": {
        "label": "",
        "href": ""
      },
      "flag": ""
    },
    {
      "contentType": "Review",
      "articleLabel": "",
      "expirableFlag": "exclusive",
      "images": {
        "alt": "",
        "credits": "Gareth Fuller/Press Association",
        "caption": "Sarcacens an inclusive club? They didnt look out for me",
        "crops": [
          {
            "url": "https://www.thetimes.co.uk/imageserver/image/%2Fmethode%2Ftimes%2Fprod%2Fweb%2Fbin%2Fbde50bea-247f-11ee-8c1b-d5d52b458fbd.jpg?crop=3844%2C2563%2C188%2C173",
            "ratio": "3:2"
          },
          {
            "url": "https://www.thetimes.co.uk/imageserver/image/%2Fmethode%2Ftimes%2Fprod%2Fweb%2Fbin%2Fbde50bea-247f-11ee-8c1b-d5d52b458fbd.jpg?crop=2497%2C1405%2C1041%2C169",
            "ratio": "16:9"
          },
          {
            "url": "https://www.thetimes.co.uk/imageserver/image/%2Fmethode%2Ftimes%2Fprod%2Fweb%2Fbin%2Fbde50bea-247f-11ee-8c1b-d5d52b458fbd.jpg?crop=2563%2C2563%2C828%2C173",
            "ratio": "1:1"
          },
          {
            "url": "https://www.thetimes.co.uk/imageserver/image/%2Fmethode%2Ftimes%2Fprod%2Fweb%2Fbin%2Fbde50bea-247f-11ee-8c1b-d5d52b458fbd.jpg?crop=1708%2C2563%2C1256%2C173",
            "ratio": "2:3"
          },
          {
            "url": "https://www.thetimes.co.uk/imageserver/image/%2Fmethode%2Ftimes%2Fprod%2Fweb%2Fbin%2Fbde50bea-247f-11ee-8c1b-d5d52b458fbd.jpg?crop=2050%2C2563%2C1085%2C173",
            "ratio": "4:5"
          },
          {
            "url": "https://www.thetimes.co.uk/imageserver/image/%2Fmethode%2Ftimes%2Fprod%2Fweb%2Fbin%2Fbde50bea-247f-11ee-8c1b-d5d52b458fbd.jpg?crop=3203%2C2563%2C508%2C173",
            "ratio": "5:4"
          }
        ]
      },
      "headline": "Blow for rebel clubs as court says Uefa can block Super League",
      "id": "12345",
      "url": "/article/harry-and-meghan-s-new-project-to-make-boys-less-toxic-nk5n3h70m",
      "tag": {
        "label": "",
        "href": ""
      },
      "flag": ""
    }
  ],
  "stackedModule1Articles": [
    {
      "contentType": "Profile",
      "articleLabel": "",
      "expirableFlag": "New",
      "images": {
        "alt": "",
        "credits": "Gareth Fuller/Press Association",
        "caption": "Sarcacens an inclusive club? They didnt look out for me",
        "crops": [
          {
            "url": "https://www.thetimes.co.uk/imageserver/image/%2Fmethode%2Ftimes%2Fprod%2Fweb%2Fbin%2Fbde50bea-247f-11ee-8c1b-d5d52b458fbd.jpg?crop=3844%2C2563%2C188%2C173",
            "ratio": "3:2"
          },
          {
            "url": "https://www.thetimes.co.uk/imageserver/image/%2Fmethode%2Ftimes%2Fprod%2Fweb%2Fbin%2Fbde50bea-247f-11ee-8c1b-d5d52b458fbd.jpg?crop=2497%2C1405%2C1041%2C169",
            "ratio": "16:9"
          },
          {
            "url": "https://www.thetimes.co.uk/imageserver/image/%2Fmethode%2Ftimes%2Fprod%2Fweb%2Fbin%2Fbde50bea-247f-11ee-8c1b-d5d52b458fbd.jpg?crop=2563%2C2563%2C828%2C173",
            "ratio": "1:1"
          },
          {
            "url": "https://www.thetimes.co.uk/imageserver/image/%2Fmethode%2Ftimes%2Fprod%2Fweb%2Fbin%2Fbde50bea-247f-11ee-8c1b-d5d52b458fbd.jpg?crop=1708%2C2563%2C1256%2C173",
            "ratio": "2:3"
          },
          {
            "url": "https://www.thetimes.co.uk/imageserver/image/%2Fmethode%2Ftimes%2Fprod%2Fweb%2Fbin%2Fbde50bea-247f-11ee-8c1b-d5d52b458fbd.jpg?crop=2050%2C2563%2C1085%2C173",
            "ratio": "4:5"
          },
          {
            "url": "https://www.thetimes.co.uk/imageserver/image/%2Fmethode%2Ftimes%2Fprod%2Fweb%2Fbin%2Fbde50bea-247f-11ee-8c1b-d5d52b458fbd.jpg?crop=3203%2C2563%2C508%2C173",
            "ratio": "5:4"
          }
        ]
      },
      "headline": "Short title of the card describing the main content",
      "id": "123456",
      "url": "/article/harry-and-meghan-s-new-project-to-make-boys-less-toxic-nk5n3h70m",
      "tag": {
        "label": "Tag",
        "href": "/"
      },
      "flag": ""
    },
    {
      "contentType": "Review",
      "articleLabel": "",
      "expirableFlag": "Updated",
      "images": {
        "alt": "",
        "credits": "Gareth Fuller/Press Association",
        "caption": "Sarcacens an inclusive club? They didnt look out for me",
        "crops": [
          {
            "url": "https://www.thetimes.co.uk/imageserver/image/%2Fmethode%2Ftimes%2Fprod%2Fweb%2Fbin%2Fbde50bea-247f-11ee-8c1b-d5d52b458fbd.jpg?crop=3844%2C2563%2C188%2C173",
            "ratio": "3:2"
          },
          {
            "url": "https://www.thetimes.co.uk/imageserver/image/%2Fmethode%2Ftimes%2Fprod%2Fweb%2Fbin%2Fbde50bea-247f-11ee-8c1b-d5d52b458fbd.jpg?crop=2497%2C1405%2C1041%2C169",
            "ratio": "16:9"
          },
          {
            "url": "https://www.thetimes.co.uk/imageserver/image/%2Fmethode%2Ftimes%2Fprod%2Fweb%2Fbin%2Fbde50bea-247f-11ee-8c1b-d5d52b458fbd.jpg?crop=2563%2C2563%2C828%2C173",
            "ratio": "1:1"
          },
          {
            "url": "https://www.thetimes.co.uk/imageserver/image/%2Fmethode%2Ftimes%2Fprod%2Fweb%2Fbin%2Fbde50bea-247f-11ee-8c1b-d5d52b458fbd.jpg?crop=1708%2C2563%2C1256%2C173",
            "ratio": "2:3"
          },
          {
            "url": "https://www.thetimes.co.uk/imageserver/image/%2Fmethode%2Ftimes%2Fprod%2Fweb%2Fbin%2Fbde50bea-247f-11ee-8c1b-d5d52b458fbd.jpg?crop=2050%2C2563%2C1085%2C173",
            "ratio": "4:5"
          },
          {
            "url": "https://www.thetimes.co.uk/imageserver/image/%2Fmethode%2Ftimes%2Fprod%2Fweb%2Fbin%2Fbde50bea-247f-11ee-8c1b-d5d52b458fbd.jpg?crop=3203%2C2563%2C508%2C173",
            "ratio": "5:4"
          }
        ]
      },
      "headline": "Short title of the card describing the main content",
      "id": "1234567",
      "url": "/article/harry-and-meghan-s-new-project-to-make-boys-less-toxic-nk5n3h70m",
      "tag": {
        "label": "Tag",
        "href": "/"
      },
      "flag": "Flag"
    },
    {
      "contentType": "Q&A",
      "articleLabel": "",
      "expirableFlag": "exclusive",
      "images": {
        "alt": "",
        "credits": "Gareth Fuller/Press Association",
        "caption": "Sarcacens an inclusive club? They didnt look out for me",
        "crops": [
          {
            "url": "https://www.thetimes.co.uk/imageserver/image/%2Fmethode%2Ftimes%2Fprod%2Fweb%2Fbin%2Fbde50bea-247f-11ee-8c1b-d5d52b458fbd.jpg?crop=3844%2C2563%2C188%2C173",
            "ratio": "3:2"
          },
          {
            "url": "https://www.thetimes.co.uk/imageserver/image/%2Fmethode%2Ftimes%2Fprod%2Fweb%2Fbin%2Fbde50bea-247f-11ee-8c1b-d5d52b458fbd.jpg?crop=2497%2C1405%2C1041%2C169",
            "ratio": "16:9"
          },
          {
            "url": "https://www.thetimes.co.uk/imageserver/image/%2Fmethode%2Ftimes%2Fprod%2Fweb%2Fbin%2Fbde50bea-247f-11ee-8c1b-d5d52b458fbd.jpg?crop=2563%2C2563%2C828%2C173",
            "ratio": "1:1"
          },
          {
            "url": "https://www.thetimes.co.uk/imageserver/image/%2Fmethode%2Ftimes%2Fprod%2Fweb%2Fbin%2Fbde50bea-247f-11ee-8c1b-d5d52b458fbd.jpg?crop=1708%2C2563%2C1256%2C173",
            "ratio": "2:3"
          },
          {
            "url": "https://www.thetimes.co.uk/imageserver/image/%2Fmethode%2Ftimes%2Fprod%2Fweb%2Fbin%2Fbde50bea-247f-11ee-8c1b-d5d52b458fbd.jpg?crop=2050%2C2563%2C1085%2C173",
            "ratio": "4:5"
          },
          {
            "url": "https://www.thetimes.co.uk/imageserver/image/%2Fmethode%2Ftimes%2Fprod%2Fweb%2Fbin%2Fbde50bea-247f-11ee-8c1b-d5d52b458fbd.jpg?crop=3203%2C2563%2C508%2C173",
            "ratio": "5:4"
          }
        ]
      },
      "headline": "Short title of the card describing the main content",
      "id": "12345678",
      "url": "/article/harry-and-meghan-s-new-project-to-make-boys-less-toxic-nk5n3h70m",
      "tag": {
        "label": "Tag",
        "href": "/"
      },
      "flag": ""
    },
    {
      "contentType": "Review",
      "articleLabel": "",
      "expirableFlag": "exclusive",
      "images": {
        "alt": "",
        "credits": "Gareth Fuller/Press Association",
        "caption": "Sarcacens an inclusive club? They didnt look out for me",
        "crops": [
          {
            "url": "https://www.thetimes.co.uk/imageserver/image/%2Fmethode%2Ftimes%2Fprod%2Fweb%2Fbin%2Fbde50bea-247f-11ee-8c1b-d5d52b458fbd.jpg?crop=3844%2C2563%2C188%2C173",
            "ratio": "3:2"
          },
          {
            "url": "https://www.thetimes.co.uk/imageserver/image/%2Fmethode%2Ftimes%2Fprod%2Fweb%2Fbin%2Fbde50bea-247f-11ee-8c1b-d5d52b458fbd.jpg?crop=2497%2C1405%2C1041%2C169",
            "ratio": "16:9"
          },
          {
            "url": "https://www.thetimes.co.uk/imageserver/image/%2Fmethode%2Ftimes%2Fprod%2Fweb%2Fbin%2Fbde50bea-247f-11ee-8c1b-d5d52b458fbd.jpg?crop=2563%2C2563%2C828%2C173",
            "ratio": "1:1"
          },
          {
            "url": "https://www.thetimes.co.uk/imageserver/image/%2Fmethode%2Ftimes%2Fprod%2Fweb%2Fbin%2Fbde50bea-247f-11ee-8c1b-d5d52b458fbd.jpg?crop=1708%2C2563%2C1256%2C173",
            "ratio": "2:3"
          },
          {
            "url": "https://www.thetimes.co.uk/imageserver/image/%2Fmethode%2Ftimes%2Fprod%2Fweb%2Fbin%2Fbde50bea-247f-11ee-8c1b-d5d52b458fbd.jpg?crop=2050%2C2563%2C1085%2C173",
            "ratio": "4:5"
          },
          {
            "url": "https://www.thetimes.co.uk/imageserver/image/%2Fmethode%2Ftimes%2Fprod%2Fweb%2Fbin%2Fbde50bea-247f-11ee-8c1b-d5d52b458fbd.jpg?crop=3203%2C2563%2C508%2C173",
            "ratio": "5:4"
          }
        ]
      },
      "headline": "Short title of the card describing the main content",
      "id": "123456789",
      "url": "/article/harry-and-meghan-s-new-project-to-make-boys-less-toxic-nk5n3h70m",
      "tag": {
        "label": "Tag",
        "href": "/"
      },
      "flag": "Flag"
    },
    {
      "contentType": "Review",
      "articleLabel": "",
      "expirableFlag": "Updated",
      "images": {
        "alt": "",
        "credits": "Gareth Fuller/Press Association",
        "caption": "Sarcacens an inclusive club? They didnt look out for me",
        "crops": [
          {
            "url": "https://www.thetimes.co.uk/imageserver/image/%2Fmethode%2Ftimes%2Fprod%2Fweb%2Fbin%2Fbde50bea-247f-11ee-8c1b-d5d52b458fbd.jpg?crop=3844%2C2563%2C188%2C173",
            "ratio": "3:2"
          },
          {
            "url": "https://www.thetimes.co.uk/imageserver/image/%2Fmethode%2Ftimes%2Fprod%2Fweb%2Fbin%2Fbde50bea-247f-11ee-8c1b-d5d52b458fbd.jpg?crop=2497%2C1405%2C1041%2C169",
            "ratio": "16:9"
          },
          {
            "url": "https://www.thetimes.co.uk/imageserver/image/%2Fmethode%2Ftimes%2Fprod%2Fweb%2Fbin%2Fbde50bea-247f-11ee-8c1b-d5d52b458fbd.jpg?crop=2563%2C2563%2C828%2C173",
            "ratio": "1:1"
          },
          {
            "url": "https://www.thetimes.co.uk/imageserver/image/%2Fmethode%2Ftimes%2Fprod%2Fweb%2Fbin%2Fbde50bea-247f-11ee-8c1b-d5d52b458fbd.jpg?crop=1708%2C2563%2C1256%2C173",
            "ratio": "2:3"
          },
          {
            "url": "https://www.thetimes.co.uk/imageserver/image/%2Fmethode%2Ftimes%2Fprod%2Fweb%2Fbin%2Fbde50bea-247f-11ee-8c1b-d5d52b458fbd.jpg?crop=2050%2C2563%2C1085%2C173",
            "ratio": "4:5"
          },
          {
            "url": "https://www.thetimes.co.uk/imageserver/image/%2Fmethode%2Ftimes%2Fprod%2Fweb%2Fbin%2Fbde50bea-247f-11ee-8c1b-d5d52b458fbd.jpg?crop=3203%2C2563%2C508%2C173",
            "ratio": "5:4"
          }
        ]
      },
      "headline": "Short title of the card describing the main content",
      "id": "23456789",
      "url": "/article/harry-and-meghan-s-new-project-to-make-boys-less-toxic-nk5n3h70m",
      "tag": {
        "label": "Tag",
        "href": "/"
      },
      "flag": ""
    },
    {
      "contentType": "Review",
      "articleLabel": "",
      "expirableFlag": "New",
      "images": {
        "alt": "",
        "credits": "Gareth Fuller/Press Association",
        "caption": "Sarcacens an inclusive club? They didnt look out for me",
        "crops": [
          {
            "url": "https://www.thetimes.co.uk/imageserver/image/%2Fmethode%2Ftimes%2Fprod%2Fweb%2Fbin%2Fbde50bea-247f-11ee-8c1b-d5d52b458fbd.jpg?crop=3844%2C2563%2C188%2C173",
            "ratio": "3:2"
          },
          {
            "url": "https://www.thetimes.co.uk/imageserver/image/%2Fmethode%2Ftimes%2Fprod%2Fweb%2Fbin%2Fbde50bea-247f-11ee-8c1b-d5d52b458fbd.jpg?crop=2497%2C1405%2C1041%2C169",
            "ratio": "16:9"
          },
          {
            "url": "https://www.thetimes.co.uk/imageserver/image/%2Fmethode%2Ftimes%2Fprod%2Fweb%2Fbin%2Fbde50bea-247f-11ee-8c1b-d5d52b458fbd.jpg?crop=2563%2C2563%2C828%2C173",
            "ratio": "1:1"
          },
          {
            "url": "https://www.thetimes.co.uk/imageserver/image/%2Fmethode%2Ftimes%2Fprod%2Fweb%2Fbin%2Fbde50bea-247f-11ee-8c1b-d5d52b458fbd.jpg?crop=1708%2C2563%2C1256%2C173",
            "ratio": "2:3"
          },
          {
            "url": "https://www.thetimes.co.uk/imageserver/image/%2Fmethode%2Ftimes%2Fprod%2Fweb%2Fbin%2Fbde50bea-247f-11ee-8c1b-d5d52b458fbd.jpg?crop=2050%2C2563%2C1085%2C173",
            "ratio": "4:5"
          },
          {
            "url": "https://www.thetimes.co.uk/imageserver/image/%2Fmethode%2Ftimes%2Fprod%2Fweb%2Fbin%2Fbde50bea-247f-11ee-8c1b-d5d52b458fbd.jpg?crop=3203%2C2563%2C508%2C173",
            "ratio": "5:4"
          }
        ]
      },
      "headline": "Short title of the card describing the main content",
      "id": "3456789",
      "url": "/article/harry-and-meghan-s-new-project-to-make-boys-less-toxic-nk5n3h70m",
      "tag": {
        "label": "Tag",
        "href": "/"
      },
      "flag": "Flag"
    },
    {
      "contentType": "Review",
      "articleLabel": "",
      "expirableFlag": "exclusive",
      "images": {
        "alt": "",
        "credits": "Gareth Fuller/Press Association",
        "caption": "Sarcacens an inclusive club? They didnt look out for me",
        "crops": [
          {
            "url": "https://www.thetimes.co.uk/imageserver/image/%2Fmethode%2Ftimes%2Fprod%2Fweb%2Fbin%2Fbde50bea-247f-11ee-8c1b-d5d52b458fbd.jpg?crop=3844%2C2563%2C188%2C173",
            "ratio": "3:2"
          },
          {
            "url": "https://www.thetimes.co.uk/imageserver/image/%2Fmethode%2Ftimes%2Fprod%2Fweb%2Fbin%2Fbde50bea-247f-11ee-8c1b-d5d52b458fbd.jpg?crop=2497%2C1405%2C1041%2C169",
            "ratio": "16:9"
          },
          {
            "url": "https://www.thetimes.co.uk/imageserver/image/%2Fmethode%2Ftimes%2Fprod%2Fweb%2Fbin%2Fbde50bea-247f-11ee-8c1b-d5d52b458fbd.jpg?crop=2563%2C2563%2C828%2C173",
            "ratio": "1:1"
          },
          {
            "url": "https://www.thetimes.co.uk/imageserver/image/%2Fmethode%2Ftimes%2Fprod%2Fweb%2Fbin%2Fbde50bea-247f-11ee-8c1b-d5d52b458fbd.jpg?crop=1708%2C2563%2C1256%2C173",
            "ratio": "2:3"
          },
          {
            "url": "https://www.thetimes.co.uk/imageserver/image/%2Fmethode%2Ftimes%2Fprod%2Fweb%2Fbin%2Fbde50bea-247f-11ee-8c1b-d5d52b458fbd.jpg?crop=2050%2C2563%2C1085%2C173",
            "ratio": "4:5"
          },
          {
            "url": "https://www.thetimes.co.uk/imageserver/image/%2Fmethode%2Ftimes%2Fprod%2Fweb%2Fbin%2Fbde50bea-247f-11ee-8c1b-d5d52b458fbd.jpg?crop=3203%2C2563%2C508%2C173",
            "ratio": "5:4"
          }
        ]
      },
      "headline": "Short title of the card describing the main content",
      "id": "456789",
      "url": "/article/harry-and-meghan-s-new-project-to-make-boys-less-toxic-nk5n3h70m",
      "tag": {
        "label": "Tag",
        "href": "/"
      },
      "flag": ""
    },
    {
      "contentType": "Q&A",
      "articleLabel": "",
      "expirableFlag": "Updated",
      "images": {
        "alt": "",
        "credits": "Gareth Fuller/Press Association",
        "caption": "Sarcacens an inclusive club? They didnt look out for me",
        "crops": [
          {
            "url": "https://www.thetimes.co.uk/imageserver/image/%2Fmethode%2Ftimes%2Fprod%2Fweb%2Fbin%2Fbde50bea-247f-11ee-8c1b-d5d52b458fbd.jpg?crop=3844%2C2563%2C188%2C173",
            "ratio": "3:2"
          },
          {
            "url": "https://www.thetimes.co.uk/imageserver/image/%2Fmethode%2Ftimes%2Fprod%2Fweb%2Fbin%2Fbde50bea-247f-11ee-8c1b-d5d52b458fbd.jpg?crop=2497%2C1405%2C1041%2C169",
            "ratio": "16:9"
          },
          {
            "url": "https://www.thetimes.co.uk/imageserver/image/%2Fmethode%2Ftimes%2Fprod%2Fweb%2Fbin%2Fbde50bea-247f-11ee-8c1b-d5d52b458fbd.jpg?crop=2563%2C2563%2C828%2C173",
            "ratio": "1:1"
          },
          {
            "url": "https://www.thetimes.co.uk/imageserver/image/%2Fmethode%2Ftimes%2Fprod%2Fweb%2Fbin%2Fbde50bea-247f-11ee-8c1b-d5d52b458fbd.jpg?crop=1708%2C2563%2C1256%2C173",
            "ratio": "2:3"
          },
          {
            "url": "https://www.thetimes.co.uk/imageserver/image/%2Fmethode%2Ftimes%2Fprod%2Fweb%2Fbin%2Fbde50bea-247f-11ee-8c1b-d5d52b458fbd.jpg?crop=2050%2C2563%2C1085%2C173",
            "ratio": "4:5"
          },
          {
            "url": "https://www.thetimes.co.uk/imageserver/image/%2Fmethode%2Ftimes%2Fprod%2Fweb%2Fbin%2Fbde50bea-247f-11ee-8c1b-d5d52b458fbd.jpg?crop=3203%2C2563%2C508%2C173",
            "ratio": "5:4"
          }
        ]
      },
      "headline": "Short title of the card describing the main content",
      "id": "56789",
      "url": "/article/harry-and-meghan-s-new-project-to-make-boys-less-toxic-nk5n3h70m",
      "tag": {
        "label": "Tag",
        "href": "/"
      },
      "flag": "Flag"
    }
  ],
  "comments": [
    {
      "byline": "Deborah Haynes",
      "headline": "Now is Willis’s chance to show he’s got more to offer than Curry",
      "id": "6789",
      "flag": "3 mins ago",
      "images": {
        "alt": "",
        "credits": "Gareth Fuller/Press Association",
        "caption": "Sarcacens an inclusive club? They didnt look out for me",
        "crops": [
          {
            "url": "https://www.thetimes.co.uk/d/img/profile/deborah-haynes.jpg",
            "ratio": "3:2"
          },
          {
            "url": "https://www.thetimes.co.uk/imageserver/image/%2Fmethode%2Ftimes%2Fprod%2Fweb%2Fbin%2Fbde50bea-247f-11ee-8c1b-d5d52b458fbd.jpg?crop=2497%2C1405%2C1041%2C169",
            "ratio": "16:9"
          },
          {
            "url": "https://www.thetimes.co.uk/d/img/profile/deborah-haynes.jpg",
            "ratio": "1:1"
          },
          {
            "url": "https://www.thetimes.co.uk/imageserver/image/%2Fmethode%2Ftimes%2Fprod%2Fweb%2Fbin%2Fbde50bea-247f-11ee-8c1b-d5d52b458fbd.jpg?crop=1708%2C2563%2C1256%2C173",
            "ratio": "2:3"
          },
          {
            "url": "https://www.thetimes.co.uk/imageserver/image/%2Fmethode%2Ftimes%2Fprod%2Fweb%2Fbin%2Fbde50bea-247f-11ee-8c1b-d5d52b458fbd.jpg?crop=2050%2C2563%2C1085%2C173",
            "ratio": "4:5"
          },
          {
            "url": "https://www.thetimes.co.uk/imageserver/image/%2Fmethode%2Ftimes%2Fprod%2Fweb%2Fbin%2Fbde50bea-247f-11ee-8c1b-d5d52b458fbd.jpg?crop=3203%2C2563%2C508%2C173",
            "ratio": "5:4"
          }
        ]
      },
      "url": "https://www.thetimes.co.uk/imageserver/image/%2Fmethode%2Ftimes%2Fprod%2Fweb%2Fbin%2Fbde50bea-247f-11ee-8c1b-d5d52b458fbd.jpg?crop=2563%2C2563%2C828%2C173"
    },
    {
      "byline": "Deborah Haynes 2",
      "headline": "Now is Willis’s chance to show he’s got more to offer than Curry",
      "id": "789",
      "flag": "21 mins ago",
      "images": {
        "alt": "",
        "credits": "Gareth Fuller/Press Association",
        "caption": "Sarcacens an inclusive club? They didnt look out for me",
        "crops": [
          {
            "url": "https://www.thetimes.co.uk/d/img/profile/deborah-haynes.jpg",
            "ratio": "3:2"
          },
          {
            "url": "https://www.thetimes.co.uk/imageserver/image/%2Fmethode%2Ftimes%2Fprod%2Fweb%2Fbin%2Fbde50bea-247f-11ee-8c1b-d5d52b458fbd.jpg?crop=2497%2C1405%2C1041%2C169",
            "ratio": "16:9"
          },
          {
            "url": "https://www.thetimes.co.uk/d/img/profile/deborah-haynes.jpg",
            "ratio": "1:1"
          },
          {
            "url": "https://www.thetimes.co.uk/imageserver/image/%2Fmethode%2Ftimes%2Fprod%2Fweb%2Fbin%2Fbde50bea-247f-11ee-8c1b-d5d52b458fbd.jpg?crop=1708%2C2563%2C1256%2C173",
            "ratio": "2:3"
          },
          {
            "url": "https://www.thetimes.co.uk/imageserver/image/%2Fmethode%2Ftimes%2Fprod%2Fweb%2Fbin%2Fbde50bea-247f-11ee-8c1b-d5d52b458fbd.jpg?crop=2050%2C2563%2C1085%2C173",
            "ratio": "4:5"
          },
          {
            "url": "https://www.thetimes.co.uk/imageserver/image/%2Fmethode%2Ftimes%2Fprod%2Fweb%2Fbin%2Fbde50bea-247f-11ee-8c1b-d5d52b458fbd.jpg?crop=3203%2C2563%2C508%2C173",
            "ratio": "5:4"
          }
        ]
      },
      "url": "https://www.thetimes.co.uk/imageserver/image/%2Fmethode%2Ftimes%2Fprod%2Fweb%2Fbin%2Fbde50bea-247f-11ee-8c1b-d5d52b458fbd.jpg?crop=2563%2C2563%2C828%2C173"
    }
  ],
  "articleStackOne": {
    "section": {
      "title": "Title bar",
      "href": "https://www.thetimes.co.uk/"
    },
    "articles": [
      {
        "contentType": "Q&A",
        "articleLabel": "",
        "expirableFlag": "Breaking",
        "images": {
          "alt": "",
          "credits": "Gareth Fuller/Press Association",
          "caption": "Sarcacens an inclusive club? They didnt look out for me",
          "crops": [
            {
              "url": "https://www.thetimes.co.uk/imageserver/image/%2Fmethode%2Ftimes%2Fprod%2Fweb%2Fbin%2Fbde50bea-247f-11ee-8c1b-d5d52b458fbd.jpg?crop=3844%2C2563%2C188%2C173",
              "ratio": "3:2"
            },
            {
              "url": "https://www.thetimes.co.uk/imageserver/image/%2Fmethode%2Ftimes%2Fprod%2Fweb%2Fbin%2Fbde50bea-247f-11ee-8c1b-d5d52b458fbd.jpg?crop=2497%2C1405%2C1041%2C169",
              "ratio": "16:9"
            },
            {
              "url": "https://www.thetimes.co.uk/imageserver/image/%2Fmethode%2Ftimes%2Fprod%2Fweb%2Fbin%2Fbde50bea-247f-11ee-8c1b-d5d52b458fbd.jpg?crop=2563%2C2563%2C828%2C173",
              "ratio": "1:1"
            },
            {
              "url": "https://www.thetimes.co.uk/imageserver/image/%2Fmethode%2Ftimes%2Fprod%2Fweb%2Fbin%2Fbde50bea-247f-11ee-8c1b-d5d52b458fbd.jpg?crop=1708%2C2563%2C1256%2C173",
              "ratio": "2:3"
            },
            {
              "url": "https://www.thetimes.co.uk/imageserver/image/%2Fmethode%2Ftimes%2Fprod%2Fweb%2Fbin%2Fbde50bea-247f-11ee-8c1b-d5d52b458fbd.jpg?crop=2050%2C2563%2C1085%2C173",
              "ratio": "4:5"
            },
            {
              "url": "https://www.thetimes.co.uk/imageserver/image/%2Fmethode%2Ftimes%2Fprod%2Fweb%2Fbin%2Fbde50bea-247f-11ee-8c1b-d5d52b458fbd.jpg?crop=3203%2C2563%2C508%2C173",
              "ratio": "5:4"
            }
          ]
        },
        "headline": "Short title of the card describing the main content",
        "id": "89",
        "url": "/article/harry-and-meghan-s-new-project-to-make-boys-less-toxic-nk5n3h70m",
        "tag": {
          "label": "",
          "href": ""
        },
        "flag": ""
      },
      {
        "contentType": "Review",
        "articleLabel": "",
        "expirableFlag": "Breaking",
        "images": {
          "alt": "",
          "credits": "Gareth Fuller/Press Association",
          "caption": "Sarcacens an inclusive club? They didnt look out for me",
          "crops": [
            {
              "url": "https://www.thetimes.co.uk/imageserver/image/%2Fmethode%2Ftimes%2Fprod%2Fweb%2Fbin%2Fbde50bea-247f-11ee-8c1b-d5d52b458fbd.jpg?crop=3844%2C2563%2C188%2C173",
              "ratio": "3:2"
            },
            {
              "url": "https://www.thetimes.co.uk/imageserver/image/%2Fmethode%2Ftimes%2Fprod%2Fweb%2Fbin%2Fbde50bea-247f-11ee-8c1b-d5d52b458fbd.jpg?crop=2497%2C1405%2C1041%2C169",
              "ratio": "16:9"
            },
            {
              "url": "https://www.thetimes.co.uk/imageserver/image/%2Fmethode%2Ftimes%2Fprod%2Fweb%2Fbin%2Fbde50bea-247f-11ee-8c1b-d5d52b458fbd.jpg?crop=2563%2C2563%2C828%2C173",
              "ratio": "1:1"
            },
            {
              "url": "https://www.thetimes.co.uk/imageserver/image/%2Fmethode%2Ftimes%2Fprod%2Fweb%2Fbin%2Fbde50bea-247f-11ee-8c1b-d5d52b458fbd.jpg?crop=1708%2C2563%2C1256%2C173",
              "ratio": "2:3"
            },
            {
              "url": "https://www.thetimes.co.uk/imageserver/image/%2Fmethode%2Ftimes%2Fprod%2Fweb%2Fbin%2Fbde50bea-247f-11ee-8c1b-d5d52b458fbd.jpg?crop=2050%2C2563%2C1085%2C173",
              "ratio": "4:5"
            },
            {
              "url": "https://www.thetimes.co.uk/imageserver/image/%2Fmethode%2Ftimes%2Fprod%2Fweb%2Fbin%2Fbde50bea-247f-11ee-8c1b-d5d52b458fbd.jpg?crop=3203%2C2563%2C508%2C173",
              "ratio": "5:4"
            }
          ]
        },
        "headline": "Short title of the card describing the main content",
        "id": "9",
        "url": "/article/harry-and-meghan-s-new-project-to-make-boys-less-toxic-nk5n3h70m",
        "tag": {
          "label": "",
          "href": ""
        },
        "flag": ""
      },
      {
        "contentType": "Review",
        "articleLabel": "",
        "expirableFlag": "New",
        "images": {
          "alt": "",
          "credits": "Gareth Fuller/Press Association",
          "caption": "Sarcacens an inclusive club? They didnt look out for me",
          "crops": [
            {
              "url": "https://www.thetimes.co.uk/imageserver/image/%2Fmethode%2Ftimes%2Fprod%2Fweb%2Fbin%2Fbde50bea-247f-11ee-8c1b-d5d52b458fbd.jpg?crop=3844%2C2563%2C188%2C173",
              "ratio": "3:2"
            },
            {
              "url": "https://www.thetimes.co.uk/imageserver/image/%2Fmethode%2Ftimes%2Fprod%2Fweb%2Fbin%2Fbde50bea-247f-11ee-8c1b-d5d52b458fbd.jpg?crop=2497%2C1405%2C1041%2C169",
              "ratio": "16:9"
            },
            {
              "url": "https://www.thetimes.co.uk/imageserver/image/%2Fmethode%2Ftimes%2Fprod%2Fweb%2Fbin%2Fbde50bea-247f-11ee-8c1b-d5d52b458fbd.jpg?crop=2563%2C2563%2C828%2C173",
              "ratio": "1:1"
            },
            {
              "url": "https://www.thetimes.co.uk/imageserver/image/%2Fmethode%2Ftimes%2Fprod%2Fweb%2Fbin%2Fbde50bea-247f-11ee-8c1b-d5d52b458fbd.jpg?crop=1708%2C2563%2C1256%2C173",
              "ratio": "2:3"
            },
            {
              "url": "https://www.thetimes.co.uk/imageserver/image/%2Fmethode%2Ftimes%2Fprod%2Fweb%2Fbin%2Fbde50bea-247f-11ee-8c1b-d5d52b458fbd.jpg?crop=2050%2C2563%2C1085%2C173",
              "ratio": "4:5"
            },
            {
              "url": "https://www.thetimes.co.uk/imageserver/image/%2Fmethode%2Ftimes%2Fprod%2Fweb%2Fbin%2Fbde50bea-247f-11ee-8c1b-d5d52b458fbd.jpg?crop=3203%2C2563%2C508%2C173",
              "ratio": "5:4"
            }
          ]
        },
        "headline": "Short title of the card describing the main content",
        "id": "98",
        "url": "/article/harry-and-meghan-s-new-project-to-make-boys-less-toxic-nk5n3h70m",
        "tag": {
          "label": "",
          "href": ""
        },
        "flag": ""
      }
    ]
  },
  "articleStackTwo": {
    "section": {
      "title": "Title bar",
      "href": "https://www.thetimes.co.uk/"
    },
    "articles": [
      {
        "contentType": "Review",
        "articleLabel": "",
        "expirableFlag": "exclusive",
        "images": {
          "alt": "",
          "credits": "Gareth Fuller/Press Association",
          "caption": "Sarcacens an inclusive club? They didnt look out for me",
          "crops": [
            {
              "url": "https://www.thetimes.co.uk/imageserver/image/%2Fmethode%2Ftimes%2Fprod%2Fweb%2Fbin%2Fbde50bea-247f-11ee-8c1b-d5d52b458fbd.jpg?crop=3844%2C2563%2C188%2C173",
              "ratio": "3:2"
            },
            {
              "url": "https://www.thetimes.co.uk/imageserver/image/%2Fmethode%2Ftimes%2Fprod%2Fweb%2Fbin%2Fbde50bea-247f-11ee-8c1b-d5d52b458fbd.jpg?crop=2497%2C1405%2C1041%2C169",
              "ratio": "16:9"
            },
            {
              "url": "https://www.thetimes.co.uk/imageserver/image/%2Fmethode%2Ftimes%2Fprod%2Fweb%2Fbin%2Fbde50bea-247f-11ee-8c1b-d5d52b458fbd.jpg?crop=2563%2C2563%2C828%2C173",
              "ratio": "1:1"
            },
            {
              "url": "https://www.thetimes.co.uk/imageserver/image/%2Fmethode%2Ftimes%2Fprod%2Fweb%2Fbin%2Fbde50bea-247f-11ee-8c1b-d5d52b458fbd.jpg?crop=1708%2C2563%2C1256%2C173",
              "ratio": "2:3"
            },
            {
              "url": "https://www.thetimes.co.uk/imageserver/image/%2Fmethode%2Ftimes%2Fprod%2Fweb%2Fbin%2Fbde50bea-247f-11ee-8c1b-d5d52b458fbd.jpg?crop=2050%2C2563%2C1085%2C173",
              "ratio": "4:5"
            },
            {
              "url": "https://www.thetimes.co.uk/imageserver/image/%2Fmethode%2Ftimes%2Fprod%2Fweb%2Fbin%2Fbde50bea-247f-11ee-8c1b-d5d52b458fbd.jpg?crop=3203%2C2563%2C508%2C173",
              "ratio": "5:4"
            }
          ]
        },
        "headline": "Short title of the card describing the main content",
        "id": "987",
        "url": "/article/harry-and-meghan-s-new-project-to-make-boys-less-toxic-nk5n3h70m",
        "tag": {
          "label": "",
          "href": ""
        },
        "flag": ""
      },
      {
        "contentType": "Review",
        "articleLabel": "",
        "expirableFlag": "Breaking",
        "images": {
          "alt": "",
          "credits": "Gareth Fuller/Press Association",
          "caption": "Sarcacens an inclusive club? They didnt look out for me",
          "crops": [
            {
              "url": "https://www.thetimes.co.uk/imageserver/image/%2Fmethode%2Ftimes%2Fprod%2Fweb%2Fbin%2Fbde50bea-247f-11ee-8c1b-d5d52b458fbd.jpg?crop=3844%2C2563%2C188%2C173",
              "ratio": "3:2"
            },
            {
              "url": "https://www.thetimes.co.uk/imageserver/image/%2Fmethode%2Ftimes%2Fprod%2Fweb%2Fbin%2Fbde50bea-247f-11ee-8c1b-d5d52b458fbd.jpg?crop=2497%2C1405%2C1041%2C169",
              "ratio": "16:9"
            },
            {
              "url": "https://www.thetimes.co.uk/imageserver/image/%2Fmethode%2Ftimes%2Fprod%2Fweb%2Fbin%2Fbde50bea-247f-11ee-8c1b-d5d52b458fbd.jpg?crop=2563%2C2563%2C828%2C173",
              "ratio": "1:1"
            },
            {
              "url": "https://www.thetimes.co.uk/imageserver/image/%2Fmethode%2Ftimes%2Fprod%2Fweb%2Fbin%2Fbde50bea-247f-11ee-8c1b-d5d52b458fbd.jpg?crop=1708%2C2563%2C1256%2C173",
              "ratio": "2:3"
            },
            {
              "url": "https://www.thetimes.co.uk/imageserver/image/%2Fmethode%2Ftimes%2Fprod%2Fweb%2Fbin%2Fbde50bea-247f-11ee-8c1b-d5d52b458fbd.jpg?crop=2050%2C2563%2C1085%2C173",
              "ratio": "4:5"
            },
            {
              "url": "https://www.thetimes.co.uk/imageserver/image/%2Fmethode%2Ftimes%2Fprod%2Fweb%2Fbin%2Fbde50bea-247f-11ee-8c1b-d5d52b458fbd.jpg?crop=3203%2C2563%2C508%2C173",
              "ratio": "5:4"
            }
          ]
        },
        "headline": "Short title of the card describing the main content",
        "id": "9876",
        "url": "/article/harry-and-meghan-s-new-project-to-make-boys-less-toxic-nk5n3h70m",
        "tag": {
          "label": "",
          "href": ""
        },
        "flag": ""
      },
      {
        "contentType": "Review",
        "articleLabel": "",
        "expirableFlag": "New",
        "images": {
          "alt": "",
          "credits": "Gareth Fuller/Press Association",
          "caption": "Sarcacens an inclusive club? They didnt look out for me",
          "crops": [
            {
              "url": "https://www.thetimes.co.uk/imageserver/image/%2Fmethode%2Ftimes%2Fprod%2Fweb%2Fbin%2Fbde50bea-247f-11ee-8c1b-d5d52b458fbd.jpg?crop=3844%2C2563%2C188%2C173",
              "ratio": "3:2"
            },
            {
              "url": "https://www.thetimes.co.uk/imageserver/image/%2Fmethode%2Ftimes%2Fprod%2Fweb%2Fbin%2Fbde50bea-247f-11ee-8c1b-d5d52b458fbd.jpg?crop=2497%2C1405%2C1041%2C169",
              "ratio": "16:9"
            },
            {
              "url": "https://www.thetimes.co.uk/imageserver/image/%2Fmethode%2Ftimes%2Fprod%2Fweb%2Fbin%2Fbde50bea-247f-11ee-8c1b-d5d52b458fbd.jpg?crop=2563%2C2563%2C828%2C173",
              "ratio": "1:1"
            },
            {
              "url": "https://www.thetimes.co.uk/imageserver/image/%2Fmethode%2Ftimes%2Fprod%2Fweb%2Fbin%2Fbde50bea-247f-11ee-8c1b-d5d52b458fbd.jpg?crop=1708%2C2563%2C1256%2C173",
              "ratio": "2:3"
            },
            {
              "url": "https://www.thetimes.co.uk/imageserver/image/%2Fmethode%2Ftimes%2Fprod%2Fweb%2Fbin%2Fbde50bea-247f-11ee-8c1b-d5d52b458fbd.jpg?crop=2050%2C2563%2C1085%2C173",
              "ratio": "4:5"
            },
            {
              "url": "https://www.thetimes.co.uk/imageserver/image/%2Fmethode%2Ftimes%2Fprod%2Fweb%2Fbin%2Fbde50bea-247f-11ee-8c1b-d5d52b458fbd.jpg?crop=3203%2C2563%2C508%2C173",
              "ratio": "5:4"
            }
          ]
        },
        "headline": "Short title of the card describing the main content",
        "id": "98765",
        "url": "/article/harry-and-meghan-s-new-project-to-make-boys-less-toxic-nk5n3h70m",
        "tag": {
          "label": "",
          "href": ""
        },
        "flag": ""
      }
    ]
  },
  "articleStackThree": {
    "section": {
      "title": "Title bar",
      "href": "https://www.thetimes.co.uk/"
    },
    "articles": [
      {
        "contentType": "Review",
        "articleLabel": "",
        "expirableFlag": "exclusive",
        "images": {
          "alt": "",
          "credits": "Gareth Fuller/Press Association",
          "caption": "Sarcacens an inclusive club? They didnt look out for me",
          "crops": [
            {
              "url": "https://www.thetimes.co.uk/imageserver/image/%2Fmethode%2Ftimes%2Fprod%2Fweb%2Fbin%2Fbde50bea-247f-11ee-8c1b-d5d52b458fbd.jpg?crop=3844%2C2563%2C188%2C173",
              "ratio": "3:2"
            },
            {
              "url": "https://www.thetimes.co.uk/imageserver/image/%2Fmethode%2Ftimes%2Fprod%2Fweb%2Fbin%2Fbde50bea-247f-11ee-8c1b-d5d52b458fbd.jpg?crop=2497%2C1405%2C1041%2C169",
              "ratio": "16:9"
            },
            {
              "url": "https://www.thetimes.co.uk/imageserver/image/%2Fmethode%2Ftimes%2Fprod%2Fweb%2Fbin%2Fbde50bea-247f-11ee-8c1b-d5d52b458fbd.jpg?crop=2563%2C2563%2C828%2C173",
              "ratio": "1:1"
            },
            {
              "url": "https://www.thetimes.co.uk/imageserver/image/%2Fmethode%2Ftimes%2Fprod%2Fweb%2Fbin%2Fbde50bea-247f-11ee-8c1b-d5d52b458fbd.jpg?crop=1708%2C2563%2C1256%2C173",
              "ratio": "2:3"
            },
            {
              "url": "https://www.thetimes.co.uk/imageserver/image/%2Fmethode%2Ftimes%2Fprod%2Fweb%2Fbin%2Fbde50bea-247f-11ee-8c1b-d5d52b458fbd.jpg?crop=2050%2C2563%2C1085%2C173",
              "ratio": "4:5"
            },
            {
              "url": "https://www.thetimes.co.uk/imageserver/image/%2Fmethode%2Ftimes%2Fprod%2Fweb%2Fbin%2Fbde50bea-247f-11ee-8c1b-d5d52b458fbd.jpg?crop=3203%2C2563%2C508%2C173",
              "ratio": "5:4"
            }
          ]
        },
        "headline": "Short title of the card describing the main content",
        "id": "987654",
        "url": "/article/harry-and-meghan-s-new-project-to-make-boys-less-toxic-nk5n3h70m",
        "tag": {
          "label": "",
          "href": ""
        },
        "flag": ""
      },
      {
        "contentType": "Review",
        "articleLabel": "",
        "expirableFlag": "Breaking",
        "images": {
          "alt": "",
          "credits": "Gareth Fuller/Press Association",
          "caption": "Sarcacens an inclusive club? They didnt look out for me",
          "crops": [
            {
              "url": "https://www.thetimes.co.uk/imageserver/image/%2Fmethode%2Ftimes%2Fprod%2Fweb%2Fbin%2Fbde50bea-247f-11ee-8c1b-d5d52b458fbd.jpg?crop=3844%2C2563%2C188%2C173",
              "ratio": "3:2"
            },
            {
              "url": "https://www.thetimes.co.uk/imageserver/image/%2Fmethode%2Ftimes%2Fprod%2Fweb%2Fbin%2Fbde50bea-247f-11ee-8c1b-d5d52b458fbd.jpg?crop=2497%2C1405%2C1041%2C169",
              "ratio": "16:9"
            },
            {
              "url": "https://www.thetimes.co.uk/imageserver/image/%2Fmethode%2Ftimes%2Fprod%2Fweb%2Fbin%2Fbde50bea-247f-11ee-8c1b-d5d52b458fbd.jpg?crop=2563%2C2563%2C828%2C173",
              "ratio": "1:1"
            },
            {
              "url": "https://www.thetimes.co.uk/imageserver/image/%2Fmethode%2Ftimes%2Fprod%2Fweb%2Fbin%2Fbde50bea-247f-11ee-8c1b-d5d52b458fbd.jpg?crop=1708%2C2563%2C1256%2C173",
              "ratio": "2:3"
            },
            {
              "url": "https://www.thetimes.co.uk/imageserver/image/%2Fmethode%2Ftimes%2Fprod%2Fweb%2Fbin%2Fbde50bea-247f-11ee-8c1b-d5d52b458fbd.jpg?crop=2050%2C2563%2C1085%2C173",
              "ratio": "4:5"
            },
            {
              "url": "https://www.thetimes.co.uk/imageserver/image/%2Fmethode%2Ftimes%2Fprod%2Fweb%2Fbin%2Fbde50bea-247f-11ee-8c1b-d5d52b458fbd.jpg?crop=3203%2C2563%2C508%2C173",
              "ratio": "5:4"
            }
          ]
        },
        "headline": "Short title of the card describing the main content",
        "id": "9876543",
        "url": "/article/harry-and-meghan-s-new-project-to-make-boys-less-toxic-nk5n3h70m",
        "tag": {
          "label": "",
          "href": ""
        },
        "flag": ""
      },
      {
        "contentType": "Review",
        "articleLabel": "",
        "expirableFlag": "exclusive",
        "images": {
          "alt": "",
          "credits": "Gareth Fuller/Press Association",
          "caption": "Sarcacens an inclusive club? They didnt look out for me",
          "crops": [
            {
              "url": "https://www.thetimes.co.uk/imageserver/image/%2Fmethode%2Ftimes%2Fprod%2Fweb%2Fbin%2Fbde50bea-247f-11ee-8c1b-d5d52b458fbd.jpg?crop=3844%2C2563%2C188%2C173",
              "ratio": "3:2"
            },
            {
              "url": "https://www.thetimes.co.uk/imageserver/image/%2Fmethode%2Ftimes%2Fprod%2Fweb%2Fbin%2Fbde50bea-247f-11ee-8c1b-d5d52b458fbd.jpg?crop=2497%2C1405%2C1041%2C169",
              "ratio": "16:9"
            },
            {
              "url": "https://www.thetimes.co.uk/imageserver/image/%2Fmethode%2Ftimes%2Fprod%2Fweb%2Fbin%2Fbde50bea-247f-11ee-8c1b-d5d52b458fbd.jpg?crop=2563%2C2563%2C828%2C173",
              "ratio": "1:1"
            },
            {
              "url": "https://www.thetimes.co.uk/imageserver/image/%2Fmethode%2Ftimes%2Fprod%2Fweb%2Fbin%2Fbde50bea-247f-11ee-8c1b-d5d52b458fbd.jpg?crop=1708%2C2563%2C1256%2C173",
              "ratio": "2:3"
            },
            {
              "url": "https://www.thetimes.co.uk/imageserver/image/%2Fmethode%2Ftimes%2Fprod%2Fweb%2Fbin%2Fbde50bea-247f-11ee-8c1b-d5d52b458fbd.jpg?crop=2050%2C2563%2C1085%2C173",
              "ratio": "4:5"
            },
            {
              "url": "https://www.thetimes.co.uk/imageserver/image/%2Fmethode%2Ftimes%2Fprod%2Fweb%2Fbin%2Fbde50bea-247f-11ee-8c1b-d5d52b458fbd.jpg?crop=3203%2C2563%2C508%2C173",
              "ratio": "5:4"
            }
          ]
        },
        "headline": "Short title of the card describing the main content",
        "id": "98765432",
        "url": "/article/harry-and-meghan-s-new-project-to-make-boys-less-toxic-nk5n3h70m",
        "tag": {
          "label": "",
          "href": ""
        },
        "flag": ""
      }
    ]
  },
  "articleStackFour": {
    "section": {
      "title": "Title bar",
      "href": "https://www.thetimes.co.uk/"
    },
    "articles": [
      {
        "contentType": "Review",
        "articleLabel": "",
        "expirableFlag": "Breaking",
        "images": {
          "alt": "",
          "credits": "Gareth Fuller/Press Association",
          "caption": "Sarcacens an inclusive club? They didnt look out for me",
          "crops": [
            {
              "url": "https://www.thetimes.co.uk/imageserver/image/%2Fmethode%2Ftimes%2Fprod%2Fweb%2Fbin%2Fbde50bea-247f-11ee-8c1b-d5d52b458fbd.jpg?crop=3844%2C2563%2C188%2C173",
              "ratio": "3:2"
            },
            {
              "url": "https://www.thetimes.co.uk/imageserver/image/%2Fmethode%2Ftimes%2Fprod%2Fweb%2Fbin%2Fbde50bea-247f-11ee-8c1b-d5d52b458fbd.jpg?crop=2497%2C1405%2C1041%2C169",
              "ratio": "16:9"
            },
            {
              "url": "https://www.thetimes.co.uk/imageserver/image/%2Fmethode%2Ftimes%2Fprod%2Fweb%2Fbin%2Fbde50bea-247f-11ee-8c1b-d5d52b458fbd.jpg?crop=2563%2C2563%2C828%2C173",
              "ratio": "1:1"
            },
            {
              "url": "https://www.thetimes.co.uk/imageserver/image/%2Fmethode%2Ftimes%2Fprod%2Fweb%2Fbin%2Fbde50bea-247f-11ee-8c1b-d5d52b458fbd.jpg?crop=1708%2C2563%2C1256%2C173",
              "ratio": "2:3"
            },
            {
              "url": "https://www.thetimes.co.uk/imageserver/image/%2Fmethode%2Ftimes%2Fprod%2Fweb%2Fbin%2Fbde50bea-247f-11ee-8c1b-d5d52b458fbd.jpg?crop=2050%2C2563%2C1085%2C173",
              "ratio": "4:5"
            },
            {
              "url": "https://www.thetimes.co.uk/imageserver/image/%2Fmethode%2Ftimes%2Fprod%2Fweb%2Fbin%2Fbde50bea-247f-11ee-8c1b-d5d52b458fbd.jpg?crop=3203%2C2563%2C508%2C173",
              "ratio": "5:4"
            }
          ]
        },
        "headline": "Short title of the card describing the main content",
        "id": "987654321",
        "url": "/article/harry-and-meghan-s-new-project-to-make-boys-less-toxic-nk5n3h70m",
        "tag": {
          "label": "",
          "href": ""
        },
        "flag": ""
      },
      {
        "contentType": "Review",
        "articleLabel": "",
        "expirableFlag": "New",
        "images": {
          "alt": "",
          "credits": "Gareth Fuller/Press Association",
          "caption": "Sarcacens an inclusive club? They didnt look out for me",
          "crops": [
            {
              "url": "https://www.thetimes.co.uk/imageserver/image/%2Fmethode%2Ftimes%2Fprod%2Fweb%2Fbin%2Fbde50bea-247f-11ee-8c1b-d5d52b458fbd.jpg?crop=3844%2C2563%2C188%2C173",
              "ratio": "3:2"
            },
            {
              "url": "https://www.thetimes.co.uk/imageserver/image/%2Fmethode%2Ftimes%2Fprod%2Fweb%2Fbin%2Fbde50bea-247f-11ee-8c1b-d5d52b458fbd.jpg?crop=2497%2C1405%2C1041%2C169",
              "ratio": "16:9"
            },
            {
              "url": "https://www.thetimes.co.uk/imageserver/image/%2Fmethode%2Ftimes%2Fprod%2Fweb%2Fbin%2Fbde50bea-247f-11ee-8c1b-d5d52b458fbd.jpg?crop=2563%2C2563%2C828%2C173",
              "ratio": "1:1"
            },
            {
              "url": "https://www.thetimes.co.uk/imageserver/image/%2Fmethode%2Ftimes%2Fprod%2Fweb%2Fbin%2Fbde50bea-247f-11ee-8c1b-d5d52b458fbd.jpg?crop=1708%2C2563%2C1256%2C173",
              "ratio": "2:3"
            },
            {
              "url": "https://www.thetimes.co.uk/imageserver/image/%2Fmethode%2Ftimes%2Fprod%2Fweb%2Fbin%2Fbde50bea-247f-11ee-8c1b-d5d52b458fbd.jpg?crop=2050%2C2563%2C1085%2C173",
              "ratio": "4:5"
            },
            {
              "url": "https://www.thetimes.co.uk/imageserver/image/%2Fmethode%2Ftimes%2Fprod%2Fweb%2Fbin%2Fbde50bea-247f-11ee-8c1b-d5d52b458fbd.jpg?crop=3203%2C2563%2C508%2C173",
              "ratio": "5:4"
            }
          ]
        },
        "headline": "Short title of the card describing the main content",
        "id": "19",
        "url": "/article/harry-and-meghan-s-new-project-to-make-boys-less-toxic-nk5n3h70m",
        "tag": {
          "label": "",
          "href": ""
        },
        "flag": ""
      },
      {
        "contentType": "Interview",
        "articleLabel": "",
        "expirableFlag": "Breaking",
        "images": {
          "alt": "",
          "credits": "Gareth Fuller/Press Association",
          "caption": "Sarcacens an inclusive club? They didnt look out for me",
          "crops": [
            {
              "url": "https://www.thetimes.co.uk/imageserver/image/%2Fmethode%2Ftimes%2Fprod%2Fweb%2Fbin%2Fbde50bea-247f-11ee-8c1b-d5d52b458fbd.jpg?crop=3844%2C2563%2C188%2C173",
              "ratio": "3:2"
            },
            {
              "url": "https://www.thetimes.co.uk/imageserver/image/%2Fmethode%2Ftimes%2Fprod%2Fweb%2Fbin%2Fbde50bea-247f-11ee-8c1b-d5d52b458fbd.jpg?crop=2497%2C1405%2C1041%2C169",
              "ratio": "16:9"
            },
            {
              "url": "https://www.thetimes.co.uk/imageserver/image/%2Fmethode%2Ftimes%2Fprod%2Fweb%2Fbin%2Fbde50bea-247f-11ee-8c1b-d5d52b458fbd.jpg?crop=2563%2C2563%2C828%2C173",
              "ratio": "1:1"
            },
            {
              "url": "https://www.thetimes.co.uk/imageserver/image/%2Fmethode%2Ftimes%2Fprod%2Fweb%2Fbin%2Fbde50bea-247f-11ee-8c1b-d5d52b458fbd.jpg?crop=1708%2C2563%2C1256%2C173",
              "ratio": "2:3"
            },
            {
              "url": "https://www.thetimes.co.uk/imageserver/image/%2Fmethode%2Ftimes%2Fprod%2Fweb%2Fbin%2Fbde50bea-247f-11ee-8c1b-d5d52b458fbd.jpg?crop=2050%2C2563%2C1085%2C173",
              "ratio": "4:5"
            },
            {
              "url": "https://www.thetimes.co.uk/imageserver/image/%2Fmethode%2Ftimes%2Fprod%2Fweb%2Fbin%2Fbde50bea-247f-11ee-8c1b-d5d52b458fbd.jpg?crop=3203%2C2563%2C508%2C173",
              "ratio": "5:4"
            }
          ]
        },
        "headline": "Short title of the card describing the main content",
        "id": "191",
        "url": "/article/harry-and-meghan-s-new-project-to-make-boys-less-toxic-nk5n3h70m",
        "tag": {
          "label": "",
          "href": ""
        },
        "flag": ""
      }
    ]
  }
}
